{
  "__data_type": "GIT ",
  "AreaProperties": {
    "__struct_id": 100,
    "type": "struct",
    "value": {
      "__struct_id": 100,
      "AmbientSndDay": {
        "type": "int",
        "value": 0
      },
      "AmbientSndDayVol": {
        "type": "int",
        "value": 0
      },
      "AmbientSndNight": {
        "type": "int",
        "value": 0
      },
      "AmbientSndNitVol": {
        "type": "int",
        "value": 0
      },
      "EnvAudio": {
        "type": "int",
        "value": 0
      },
      "MusicBattle": {
        "type": "int",
        "value": 534
      },
      "MusicDay": {
        "type": "int",
        "value": 537
      },
      "MusicDelay": {
        "type": "int",
        "value": 0
      },
      "MusicNight": {
        "type": "int",
        "value": 537
      }
    }
  },
  "Creature List": {
    "type": "list",
    "value": []
  },
  "Door List": {
    "type": "list",
    "value": []
  },
  "Encounter List": {
    "type": "list",
    "value": []
  },
  "List": {
    "type": "list",
    "value": []
  },
  "Placeable List": {
    "type": "list",
    "value": [
      {
        "__struct_id": 9,
        "AnimationState": {
          "type": "byte",
          "value": 0
        },
        "Appearance": {
          "type": "dword",
          "value": 1061
        },
        "AutoRemoveKey": {
          "type": "byte",
          "value": 0
        },
        "Bearing": {
          "type": "float",
          "value": -0.0
        },
        "BodyBag": {
          "type": "byte",
          "value": 0
        },
        "CloseLockDC": {
          "type": "byte",
          "value": 0
        },
        "Conversation": {
          "type": "resref",
          "value": ""
        },
        "CurrentHP": {
          "type": "short",
          "value": 10
        },
        "Description": {
          "type": "cexolocstring",
          "value": {}
        },
        "DisarmDC": {
          "type": "byte",
          "value": 0
        },
        "Faction": {
          "type": "dword",
          "value": 3
        },
        "Fort": {
          "type": "byte",
          "value": 5
        },
        "Hardness": {
          "type": "byte",
          "value": 5
        },
        "HasInventory": {
          "type": "byte",
          "value": 0
        },
        "HP": {
          "type": "short",
          "value": 10
        },
        "Interruptable": {
          "type": "byte",
          "value": 1
        },
        "KeyName": {
          "type": "cexostring",
          "value": ""
        },
        "KeyRequired": {
          "type": "byte",
          "value": 0
        },
        "Lockable": {
          "type": "byte",
          "value": 1
        },
        "Locked": {
          "type": "byte",
          "value": 0
        },
        "LocName": {
          "type": "cexolocstring",
          "value": {
            "0": "Moon, Brown (Large)"
          }
        },
        "OnClick": {
          "type": "resref",
          "value": ""
        },
        "OnClosed": {
          "type": "resref",
          "value": ""
        },
        "OnDamaged": {
          "type": "resref",
          "value": ""
        },
        "OnDeath": {
          "type": "resref",
          "value": ""
        },
        "OnDisarm": {
          "type": "resref",
          "value": ""
        },
        "OnHeartbeat": {
          "type": "resref",
          "value": ""
        },
        "OnInvDisturbed": {
          "type": "resref",
          "value": ""
        },
        "OnLock": {
          "type": "resref",
          "value": ""
        },
        "OnMeleeAttacked": {
          "type": "resref",
          "value": ""
        },
        "OnOpen": {
          "type": "resref",
          "value": ""
        },
        "OnSpellCastAt": {
          "type": "resref",
          "value": ""
        },
        "OnTrapTriggered": {
          "type": "resref",
          "value": ""
        },
        "OnUnlock": {
          "type": "resref",
          "value": ""
        },
        "OnUsed": {
          "type": "resref",
          "value": ""
        },
        "OnUserDefined": {
          "type": "resref",
          "value": ""
        },
        "OpenLockDC": {
          "type": "byte",
          "value": 0
        },
        "Plot": {
          "type": "byte",
          "value": 0
        },
        "PortraitId": {
          "type": "word",
          "value": 0
        },
        "Ref": {
          "type": "byte",
          "value": 0
        },
        "Static": {
          "type": "byte",
          "value": 1
        },
        "Tag": {
          "type": "cexostring",
          "value": "_mdrn_pl_spc_lbm"
        },
        "TemplateResRef": {
          "type": "resref",
          "value": "_mdrn_pl_spc_lbm"
        },
        "TrapDetectable": {
          "type": "byte",
          "value": 1
        },
        "TrapDetectDC": {
          "type": "byte",
          "value": 0
        },
        "TrapDisarmable": {
          "type": "byte",
          "value": 1
        },
        "TrapFlag": {
          "type": "byte",
          "value": 0
        },
        "TrapOneShot": {
          "type": "byte",
          "value": 1
        },
        "TrapType": {
          "type": "byte",
          "value": 0
        },
        "Type": {
          "type": "byte",
          "value": 0
        },
        "Useable": {
          "type": "byte",
          "value": 0
        },
        "Will": {
          "type": "byte",
          "value": 0
        },
        "X": {
          "type": "float",
          "value": 51.83480834960938
        },
        "Y": {
          "type": "float",
          "value": 67.21329498291016
        },
        "Z": {
          "type": "float",
          "value": 2.999990463256836
        }
      },
      {
        "__struct_id": 9,
        "AnimationState": {
          "type": "byte",
          "value": 0
        },
        "Appearance": {
          "type": "dword",
          "value": 6117
        },
        "AutoRemoveKey": {
          "type": "byte",
          "value": 0
        },
        "Bearing": {
          "type": "float",
          "value": 0.6135918498039246
        },
        "BodyBag": {
          "type": "byte",
          "value": 0
        },
        "CloseLockDC": {
          "type": "byte",
          "value": 0
        },
        "Conversation": {
          "type": "resref",
          "value": ""
        },
        "CurrentHP": {
          "type": "short",
          "value": 10
        },
        "Description": {
          "type": "cexolocstring",
          "value": {
            "0": ""
          }
        },
        "DisarmDC": {
          "type": "byte",
          "value": 0
        },
        "Faction": {
          "type": "dword",
          "value": 3
        },
        "Fort": {
          "type": "byte",
          "value": 5
        },
        "Hardness": {
          "type": "byte",
          "value": 5
        },
        "HasInventory": {
          "type": "byte",
          "value": 0
        },
        "HP": {
          "type": "short",
          "value": 10
        },
        "Interruptable": {
          "type": "byte",
          "value": 1
        },
        "KeyName": {
          "type": "cexostring",
          "value": ""
        },
        "KeyRequired": {
          "type": "byte",
          "value": 0
        },
        "Lockable": {
          "type": "byte",
          "value": 1
        },
        "Locked": {
          "type": "byte",
          "value": 0
        },
        "LocName": {
          "type": "cexolocstring",
          "value": {
            "0": "Asteroids"
          }
        },
        "OnClick": {
          "type": "resref",
          "value": ""
        },
        "OnClosed": {
          "type": "resref",
          "value": ""
        },
        "OnDamaged": {
          "type": "resref",
          "value": ""
        },
        "OnDeath": {
          "type": "resref",
          "value": ""
        },
        "OnDisarm": {
          "type": "resref",
          "value": ""
        },
        "OnHeartbeat": {
          "type": "resref",
          "value": ""
        },
        "OnInvDisturbed": {
          "type": "resref",
          "value": ""
        },
        "OnLock": {
          "type": "resref",
          "value": ""
        },
        "OnMeleeAttacked": {
          "type": "resref",
          "value": ""
        },
        "OnOpen": {
          "type": "resref",
          "value": ""
        },
        "OnSpellCastAt": {
          "type": "resref",
          "value": ""
        },
        "OnTrapTriggered": {
          "type": "resref",
          "value": ""
        },
        "OnUnlock": {
          "type": "resref",
          "value": ""
        },
        "OnUsed": {
          "type": "resref",
          "value": ""
        },
        "OnUserDefined": {
          "type": "resref",
          "value": ""
        },
        "OpenLockDC": {
          "type": "byte",
          "value": 0
        },
        "Plot": {
          "type": "byte",
          "value": 0
        },
        "PortraitId": {
          "type": "word",
          "value": 0
        },
        "Ref": {
          "type": "byte",
          "value": 0
        },
        "Static": {
          "type": "byte",
          "value": 1
        },
        "Tag": {
          "type": "cexostring",
          "value": "_mdrn_pl_smast3"
        },
        "TemplateResRef": {
          "type": "resref",
          "value": "_mdrn_pl_smast3"
        },
        "TrapDetectable": {
          "type": "byte",
          "value": 1
        },
        "TrapDetectDC": {
          "type": "byte",
          "value": 0
        },
        "TrapDisarmable": {
          "type": "byte",
          "value": 1
        },
        "TrapFlag": {
          "type": "byte",
          "value": 0
        },
        "TrapOneShot": {
          "type": "byte",
          "value": 1
        },
        "TrapType": {
          "type": "byte",
          "value": 0
        },
        "Type": {
          "type": "byte",
          "value": 0
        },
        "Useable": {
          "type": "byte",
          "value": 0
        },
        "Will": {
          "type": "byte",
          "value": 0
        },
        "X": {
          "type": "float",
          "value": 241.4347534179688
        },
        "Y": {
          "type": "float",
          "value": 136.310546875
        },
        "Z": {
          "type": "float",
          "value": 1.949995040893555
        }
      },
      {
        "__struct_id": 9,
        "AnimationState": {
          "type": "byte",
          "value": 0
        },
        "Appearance": {
          "type": "dword",
          "value": 6117
        },
        "AutoRemoveKey": {
          "type": "byte",
          "value": 0
        },
        "Bearing": {
          "type": "float",
          "value": 0.6135918498039246
        },
        "BodyBag": {
          "type": "byte",
          "value": 0
        },
        "CloseLockDC": {
          "type": "byte",
          "value": 0
        },
        "Conversation": {
          "type": "resref",
          "value": ""
        },
        "CurrentHP": {
          "type": "short",
          "value": 10
        },
        "Description": {
          "type": "cexolocstring",
          "value": {
            "0": ""
          }
        },
        "DisarmDC": {
          "type": "byte",
          "value": 0
        },
        "Faction": {
          "type": "dword",
          "value": 3
        },
        "Fort": {
          "type": "byte",
          "value": 5
        },
        "Hardness": {
          "type": "byte",
          "value": 5
        },
        "HasInventory": {
          "type": "byte",
          "value": 0
        },
        "HP": {
          "type": "short",
          "value": 10
        },
        "Interruptable": {
          "type": "byte",
          "value": 1
        },
        "KeyName": {
          "type": "cexostring",
          "value": ""
        },
        "KeyRequired": {
          "type": "byte",
          "value": 0
        },
        "Lockable": {
          "type": "byte",
          "value": 1
        },
        "Locked": {
          "type": "byte",
          "value": 0
        },
        "LocName": {
          "type": "cexolocstring",
          "value": {
            "0": "Asteroids"
          }
        },
        "OnClick": {
          "type": "resref",
          "value": ""
        },
        "OnClosed": {
          "type": "resref",
          "value": ""
        },
        "OnDamaged": {
          "type": "resref",
          "value": ""
        },
        "OnDeath": {
          "type": "resref",
          "value": ""
        },
        "OnDisarm": {
          "type": "resref",
          "value": ""
        },
        "OnHeartbeat": {
          "type": "resref",
          "value": ""
        },
        "OnInvDisturbed": {
          "type": "resref",
          "value": ""
        },
        "OnLock": {
          "type": "resref",
          "value": ""
        },
        "OnMeleeAttacked": {
          "type": "resref",
          "value": ""
        },
        "OnOpen": {
          "type": "resref",
          "value": ""
        },
        "OnSpellCastAt": {
          "type": "resref",
          "value": ""
        },
        "OnTrapTriggered": {
          "type": "resref",
          "value": ""
        },
        "OnUnlock": {
          "type": "resref",
          "value": ""
        },
        "OnUsed": {
          "type": "resref",
          "value": ""
        },
        "OnUserDefined": {
          "type": "resref",
          "value": ""
        },
        "OpenLockDC": {
          "type": "byte",
          "value": 0
        },
        "Plot": {
          "type": "byte",
          "value": 0
        },
        "PortraitId": {
          "type": "word",
          "value": 0
        },
        "Ref": {
          "type": "byte",
          "value": 0
        },
        "Static": {
          "type": "byte",
          "value": 1
        },
        "Tag": {
          "type": "cexostring",
          "value": "_mdrn_pl_smast3"
        },
        "TemplateResRef": {
          "type": "resref",
          "value": "_mdrn_pl_smast3"
        },
        "TrapDetectable": {
          "type": "byte",
          "value": 1
        },
        "TrapDetectDC": {
          "type": "byte",
          "value": 0
        },
        "TrapDisarmable": {
          "type": "byte",
          "value": 1
        },
        "TrapFlag": {
          "type": "byte",
          "value": 0
        },
        "TrapOneShot": {
          "type": "byte",
          "value": 1
        },
        "TrapType": {
          "type": "byte",
          "value": 0
        },
        "Type": {
          "type": "byte",
          "value": 0
        },
        "Useable": {
          "type": "byte",
          "value": 0
        },
        "Will": {
          "type": "byte",
          "value": 0
        },
        "X": {
          "type": "float",
          "value": 268.8929138183594
        },
        "Y": {
          "type": "float",
          "value": 117.7690963745117
        },
        "Z": {
          "type": "float",
          "value": 2.213589668273926
        }
      },
      {
        "__struct_id": 9,
        "AnimationState": {
          "type": "byte",
          "value": 0
        },
        "Appearance": {
          "type": "dword",
          "value": 6117
        },
        "AutoRemoveKey": {
          "type": "byte",
          "value": 0
        },
        "Bearing": {
          "type": "float",
          "value": 1.521707773208618
        },
        "BodyBag": {
          "type": "byte",
          "value": 0
        },
        "CloseLockDC": {
          "type": "byte",
          "value": 0
        },
        "Conversation": {
          "type": "resref",
          "value": ""
        },
        "CurrentHP": {
          "type": "short",
          "value": 10
        },
        "Description": {
          "type": "cexolocstring",
          "value": {
            "0": ""
          }
        },
        "DisarmDC": {
          "type": "byte",
          "value": 0
        },
        "Faction": {
          "type": "dword",
          "value": 3
        },
        "Fort": {
          "type": "byte",
          "value": 5
        },
        "Hardness": {
          "type": "byte",
          "value": 5
        },
        "HasInventory": {
          "type": "byte",
          "value": 0
        },
        "HP": {
          "type": "short",
          "value": 10
        },
        "Interruptable": {
          "type": "byte",
          "value": 1
        },
        "KeyName": {
          "type": "cexostring",
          "value": ""
        },
        "KeyRequired": {
          "type": "byte",
          "value": 0
        },
        "Lockable": {
          "type": "byte",
          "value": 1
        },
        "Locked": {
          "type": "byte",
          "value": 0
        },
        "LocName": {
          "type": "cexolocstring",
          "value": {
            "0": "Asteroids"
          }
        },
        "OnClick": {
          "type": "resref",
          "value": ""
        },
        "OnClosed": {
          "type": "resref",
          "value": ""
        },
        "OnDamaged": {
          "type": "resref",
          "value": ""
        },
        "OnDeath": {
          "type": "resref",
          "value": ""
        },
        "OnDisarm": {
          "type": "resref",
          "value": ""
        },
        "OnHeartbeat": {
          "type": "resref",
          "value": ""
        },
        "OnInvDisturbed": {
          "type": "resref",
          "value": ""
        },
        "OnLock": {
          "type": "resref",
          "value": ""
        },
        "OnMeleeAttacked": {
          "type": "resref",
          "value": ""
        },
        "OnOpen": {
          "type": "resref",
          "value": ""
        },
        "OnSpellCastAt": {
          "type": "resref",
          "value": ""
        },
        "OnTrapTriggered": {
          "type": "resref",
          "value": ""
        },
        "OnUnlock": {
          "type": "resref",
          "value": ""
        },
        "OnUsed": {
          "type": "resref",
          "value": ""
        },
        "OnUserDefined": {
          "type": "resref",
          "value": ""
        },
        "OpenLockDC": {
          "type": "byte",
          "value": 0
        },
        "Plot": {
          "type": "byte",
          "value": 0
        },
        "PortraitId": {
          "type": "word",
          "value": 0
        },
        "Ref": {
          "type": "byte",
          "value": 0
        },
        "Static": {
          "type": "byte",
          "value": 1
        },
        "Tag": {
          "type": "cexostring",
          "value": "_mdrn_pl_smast3"
        },
        "TemplateResRef": {
          "type": "resref",
          "value": "_mdrn_pl_smast3"
        },
        "TrapDetectable": {
          "type": "byte",
          "value": 1
        },
        "TrapDetectDC": {
          "type": "byte",
          "value": 0
        },
        "TrapDisarmable": {
          "type": "byte",
          "value": 1
        },
        "TrapFlag": {
          "type": "byte",
          "value": 0
        },
        "TrapOneShot": {
          "type": "byte",
          "value": 1
        },
        "TrapType": {
          "type": "byte",
          "value": 0
        },
        "Type": {
          "type": "byte",
          "value": 0
        },
        "Useable": {
          "type": "byte",
          "value": 0
        },
        "Will": {
          "type": "byte",
          "value": 0
        },
        "X": {
          "type": "float",
          "value": 235.9201354980469
        },
        "Y": {
          "type": "float",
          "value": 219.6390991210938
        },
        "Z": {
          "type": "float",
          "value": 2.050002574920654
        }
      },
      {
        "__struct_id": 9,
        "AnimationState": {
          "type": "byte",
          "value": 0
        },
        "Appearance": {
          "type": "dword",
          "value": 6117
        },
        "AutoRemoveKey": {
          "type": "byte",
          "value": 0
        },
        "Bearing": {
          "type": "float",
          "value": 0.6135918498039246
        },
        "BodyBag": {
          "type": "byte",
          "value": 0
        },
        "CloseLockDC": {
          "type": "byte",
          "value": 0
        },
        "Conversation": {
          "type": "resref",
          "value": ""
        },
        "CurrentHP": {
          "type": "short",
          "value": 10
        },
        "Description": {
          "type": "cexolocstring",
          "value": {
            "0": ""
          }
        },
        "DisarmDC": {
          "type": "byte",
          "value": 0
        },
        "Faction": {
          "type": "dword",
          "value": 3
        },
        "Fort": {
          "type": "byte",
          "value": 5
        },
        "Hardness": {
          "type": "byte",
          "value": 5
        },
        "HasInventory": {
          "type": "byte",
          "value": 0
        },
        "HP": {
          "type": "short",
          "value": 10
        },
        "Interruptable": {
          "type": "byte",
          "value": 1
        },
        "KeyName": {
          "type": "cexostring",
          "value": ""
        },
        "KeyRequired": {
          "type": "byte",
          "value": 0
        },
        "Lockable": {
          "type": "byte",
          "value": 1
        },
        "Locked": {
          "type": "byte",
          "value": 0
        },
        "LocName": {
          "type": "cexolocstring",
          "value": {
            "0": "Asteroids"
          }
        },
        "OnClick": {
          "type": "resref",
          "value": ""
        },
        "OnClosed": {
          "type": "resref",
          "value": ""
        },
        "OnDamaged": {
          "type": "resref",
          "value": ""
        },
        "OnDeath": {
          "type": "resref",
          "value": ""
        },
        "OnDisarm": {
          "type": "resref",
          "value": ""
        },
        "OnHeartbeat": {
          "type": "resref",
          "value": ""
        },
        "OnInvDisturbed": {
          "type": "resref",
          "value": ""
        },
        "OnLock": {
          "type": "resref",
          "value": ""
        },
        "OnMeleeAttacked": {
          "type": "resref",
          "value": ""
        },
        "OnOpen": {
          "type": "resref",
          "value": ""
        },
        "OnSpellCastAt": {
          "type": "resref",
          "value": ""
        },
        "OnTrapTriggered": {
          "type": "resref",
          "value": ""
        },
        "OnUnlock": {
          "type": "resref",
          "value": ""
        },
        "OnUsed": {
          "type": "resref",
          "value": ""
        },
        "OnUserDefined": {
          "type": "resref",
          "value": ""
        },
        "OpenLockDC": {
          "type": "byte",
          "value": 0
        },
        "Plot": {
          "type": "byte",
          "value": 0
        },
        "PortraitId": {
          "type": "word",
          "value": 0
        },
        "Ref": {
          "type": "byte",
          "value": 0
        },
        "Static": {
          "type": "byte",
          "value": 1
        },
        "Tag": {
          "type": "cexostring",
          "value": "_mdrn_pl_smast3"
        },
        "TemplateResRef": {
          "type": "resref",
          "value": "_mdrn_pl_smast3"
        },
        "TrapDetectable": {
          "type": "byte",
          "value": 1
        },
        "TrapDetectDC": {
          "type": "byte",
          "value": 0
        },
        "TrapDisarmable": {
          "type": "byte",
          "value": 1
        },
        "TrapFlag": {
          "type": "byte",
          "value": 0
        },
        "TrapOneShot": {
          "type": "byte",
          "value": 1
        },
        "TrapType": {
          "type": "byte",
          "value": 0
        },
        "Type": {
          "type": "byte",
          "value": 0
        },
        "Useable": {
          "type": "byte",
          "value": 0
        },
        "Will": {
          "type": "byte",
          "value": 0
        },
        "X": {
          "type": "float",
          "value": 204.0670928955078
        },
        "Y": {
          "type": "float",
          "value": 196.7085571289063
        },
        "Z": {
          "type": "float",
          "value": 2.999990463256836
        }
      },
      {
        "__struct_id": 9,
        "AnimationState": {
          "type": "byte",
          "value": 0
        },
        "Appearance": {
          "type": "dword",
          "value": 20512
        },
        "AutoRemoveKey": {
          "type": "byte",
          "value": 0
        },
        "Bearing": {
          "type": "float",
          "value": 1.595340013504028
        },
        "BodyBag": {
          "type": "byte",
          "value": 0
        },
        "CloseLockDC": {
          "type": "byte",
          "value": 0
        },
        "Conversation": {
          "type": "resref",
          "value": ""
        },
        "CurrentHP": {
          "type": "short",
          "value": 10
        },
        "Description": {
          "type": "cexolocstring",
          "value": {
            "0": ""
          }
        },
        "DisarmDC": {
          "type": "byte",
          "value": 0
        },
        "Faction": {
          "type": "dword",
          "value": 3
        },
        "Fort": {
          "type": "byte",
          "value": 5
        },
        "Hardness": {
          "type": "byte",
          "value": 5
        },
        "HasInventory": {
          "type": "byte",
          "value": 0
        },
        "HP": {
          "type": "short",
          "value": 10
        },
        "Interruptable": {
          "type": "byte",
          "value": 1
        },
        "KeyName": {
          "type": "cexostring",
          "value": ""
        },
        "KeyRequired": {
          "type": "byte",
          "value": 0
        },
        "Lockable": {
          "type": "byte",
          "value": 0
        },
        "Locked": {
          "type": "byte",
          "value": 0
        },
        "LocName": {
          "type": "cexolocstring",
          "value": {
            "0": "Docking Point: Tatooine"
          }
        },
        "OnClick": {
          "type": "resref",
          "value": ""
        },
        "OnClosed": {
          "type": "resref",
          "value": ""
        },
        "OnDamaged": {
          "type": "resref",
          "value": ""
        },
        "OnDeath": {
          "type": "resref",
          "value": ""
        },
        "OnDisarm": {
          "type": "resref",
          "value": ""
        },
        "OnHeartbeat": {
          "type": "resref",
          "value": ""
        },
        "OnInvDisturbed": {
          "type": "resref",
          "value": ""
        },
        "OnLock": {
          "type": "resref",
          "value": ""
        },
        "OnMeleeAttacked": {
          "type": "resref",
          "value": ""
        },
        "OnOpen": {
          "type": "resref",
          "value": ""
        },
        "OnSpellCastAt": {
          "type": "resref",
          "value": ""
        },
        "OnTrapTriggered": {
          "type": "resref",
          "value": ""
        },
        "OnUnlock": {
          "type": "resref",
          "value": ""
        },
        "OnUsed": {
          "type": "resref",
          "value": "generic_convo"
        },
        "OnUserDefined": {
          "type": "resref",
          "value": ""
        },
        "OpenLockDC": {
          "type": "byte",
          "value": 0
        },
        "Plot": {
          "type": "byte",
          "value": 1
        },
        "PortraitId": {
          "type": "word",
          "value": 0
        },
        "Ref": {
          "type": "byte",
          "value": 0
        },
        "Static": {
          "type": "byte",
          "value": 0
        },
        "Tag": {
          "type": "cexostring",
          "value": "spc_dock"
        },
        "TemplateResRef": {
          "type": "resref",
          "value": "spc_dock"
        },
        "TrapDetectable": {
          "type": "byte",
          "value": 1
        },
        "TrapDetectDC": {
          "type": "byte",
          "value": 0
        },
        "TrapDisarmable": {
          "type": "byte",
          "value": 1
        },
        "TrapFlag": {
          "type": "byte",
          "value": 0
        },
        "TrapOneShot": {
          "type": "byte",
          "value": 1
        },
        "TrapType": {
          "type": "byte",
          "value": 0
        },
        "Type": {
          "type": "byte",
          "value": 0
        },
        "Useable": {
          "type": "byte",
          "value": 1
        },
        "VarTable": {
          "type": "list",
          "value": [
            {
              "__struct_id": 0,
              "Name": {
                "type": "cexostring",
                "value": "CONVERSATION"
              },
              "Type": {
                "type": "dword",
                "value": 3
              },
              "Value": {
                "type": "cexostring",
                "value": "StarportDockDialog"
              }
            },
            {
              "__struct_id": 0,
              "Name": {
                "type": "cexostring",
                "value": "STARPORT_TELEPORT_WAYPOINT"
              },
              "Type": {
                "type": "dword",
                "value": 3
              },
              "Value": {
                "type": "cexostring",
                "value": "Tatooine_Orbit"
              }
            },
            {
              "__struct_id": 0,
              "Name": {
                "type": "cexostring",
                "value": "PLANET_TYPE_ID"
              },
              "Type": {
                "type": "dword",
                "value": 1
              },
              "Value": {
                "type": "int",
                "value": 2
              }
            }
          ]
        },
        "Will": {
          "type": "byte",
          "value": 0
        },
        "X": {
          "type": "float",
          "value": 83.50407409667969
        },
        "Y": {
          "type": "float",
          "value": 53.65089797973633
        },
        "Z": {
          "type": "float",
          "value": 2.999990463256836
        }
      },
      {
        "__struct_id": 9,
        "AnimationState": {
          "type": "byte",
          "value": 0
        },
        "Appearance": {
          "type": "dword",
          "value": 9488
        },
        "AutoRemoveKey": {
          "type": "byte",
          "value": 0
        },
        "Bearing": {
          "type": "float",
          "value": -2.454369068145752
        },
        "BodyBag": {
          "type": "byte",
          "value": 0
        },
        "CloseLockDC": {
          "type": "byte",
          "value": 0
        },
        "Conversation": {
          "type": "resref",
          "value": ""
        },
        "CurrentHP": {
          "type": "short",
          "value": 10
        },
        "Description": {
          "id": 14533,
          "type": "cexolocstring",
          "value": {
            "0": ""
          }
        },
        "DisarmDC": {
          "type": "byte",
          "value": 0
        },
        "Faction": {
          "type": "dword",
          "value": 1
        },
        "Fort": {
          "type": "byte",
          "value": 5
        },
        "Hardness": {
          "type": "byte",
          "value": 5
        },
        "HasInventory": {
          "type": "byte",
          "value": 0
        },
        "HP": {
          "type": "short",
          "value": 10
        },
        "Interruptable": {
          "type": "byte",
          "value": 1
        },
        "KeyName": {
          "type": "cexostring",
          "value": ""
        },
        "KeyRequired": {
          "type": "byte",
          "value": 0
        },
        "Lockable": {
          "type": "byte",
          "value": 0
        },
        "Locked": {
          "type": "byte",
          "value": 0
        },
        "LocName": {
          "id": 5670,
          "type": "cexolocstring",
          "value": {
            "0": "Starlane - Hutlar"
          }
        },
        "OnClick": {
          "type": "resref",
          "value": ""
        },
        "OnClosed": {
          "type": "resref",
          "value": ""
        },
        "OnDamaged": {
          "type": "resref",
          "value": ""
        },
        "OnDeath": {
          "type": "resref",
          "value": ""
        },
        "OnDisarm": {
          "type": "resref",
          "value": ""
        },
        "OnHeartbeat": {
          "type": "resref",
          "value": ""
        },
        "OnInvDisturbed": {
          "type": "resref",
          "value": ""
        },
        "OnLock": {
          "type": "resref",
          "value": ""
        },
        "OnMeleeAttacked": {
          "type": "resref",
          "value": ""
        },
        "OnOpen": {
          "type": "resref",
          "value": ""
        },
        "OnSpellCastAt": {
          "type": "resref",
          "value": ""
        },
        "OnTrapTriggered": {
          "type": "resref",
          "value": ""
        },
        "OnUnlock": {
          "type": "resref",
          "value": ""
        },
        "OnUsed": {
          "type": "resref",
          "value": "teleport"
        },
        "OnUserDefined": {
          "type": "resref",
          "value": ""
        },
        "OpenLockDC": {
          "type": "byte",
          "value": 0
        },
        "Plot": {
          "type": "byte",
          "value": 1
        },
        "PortraitId": {
          "type": "word",
          "value": 0
        },
        "Ref": {
          "type": "byte",
          "value": 0
        },
        "Static": {
          "type": "byte",
          "value": 0
        },
        "Tag": {
          "type": "cexostring",
          "value": "tele_obj"
        },
        "TemplateResRef": {
          "type": "resref",
          "value": "tele_obj"
        },
        "TrapDetectable": {
          "type": "byte",
          "value": 1
        },
        "TrapDetectDC": {
          "type": "byte",
          "value": 0
        },
        "TrapDisarmable": {
          "type": "byte",
          "value": 1
        },
        "TrapFlag": {
          "type": "byte",
          "value": 0
        },
        "TrapOneShot": {
          "type": "byte",
          "value": 1
        },
        "TrapType": {
          "type": "byte",
          "value": 0
        },
        "Type": {
          "type": "byte",
          "value": 0
        },
        "Useable": {
          "type": "byte",
          "value": 1
        },
        "VarTable": {
          "type": "list",
          "value": [
            {
              "__struct_id": 0,
              "Name": {
                "type": "cexostring",
                "value": "SCRIPT_1"
              },
              "Type": {
                "type": "dword",
                "value": 3
              },
              "Value": {
                "type": "cexostring",
                "value": "Placeable.WarpDevice.OnUsed"
              }
            },
            {
              "__struct_id": 0,
              "Name": {
                "type": "cexostring",
                "value": "DESTINATION"
              },
              "Type": {
                "type": "dword",
                "value": 3
              },
              "Value": {
                "type": "cexostring",
                "value": "STARLANE_LANDING_HUTLAR_2"
              }
            },
            {
              "__struct_id": 0,
              "Name": {
                "type": "cexostring",
                "value": "VISUAL_EFFECT"
              },
              "Type": {
                "type": "dword",
                "value": 1
              },
              "Value": {
                "type": "int",
                "value": 0
              }
            },
            {
              "__struct_id": 0,
              "Name": {
                "type": "cexostring",
                "value": "MISSING_KEY_ITEM_MESSAGE"
              },
              "Type": {
                "type": "dword",
                "value": 3
              },
              "Value": {
                "type": "cexostring",
                "value": ""
              }
            },
            {
              "__struct_id": 0,
              "Name": {
                "type": "cexostring",
                "value": "KEY_ITEM_ID"
              },
              "Type": {
                "type": "dword",
                "value": 1
              },
              "Value": {
                "type": "int",
                "value": 0
              }
            },
            {
              "__struct_id": 0,
              "Name": {
                "type": "cexostring",
                "value": "VISIBILITY_OBJECT_ID"
              },
              "Type": {
                "type": "dword",
                "value": 3
              },
              "Value": {
                "type": "cexostring",
                "value": ""
              }
            },
            {
              "__struct_id": 0,
              "Name": {
                "type": "cexostring",
                "value": "VISIBILITY_HIDDEN_DEFAULT"
              },
              "Type": {
                "type": "dword",
                "value": 1
              },
              "Value": {
                "type": "int",
                "value": 0
              }
            }
          ]
        },
        "Will": {
          "type": "byte",
          "value": 0
        },
        "X": {
          "type": "float",
          "value": 298.588623046875
        },
        "Y": {
          "type": "float",
          "value": 20.39798736572266
        },
        "Z": {
          "type": "float",
          "value": 2.999990463256836
        }
      }
    ]
  },
  "SoundList": {
    "type": "list",
    "value": []
  },
  "StoreList": {
    "type": "list",
    "value": []
  },
  "TriggerList": {
    "type": "list",
    "value": [
      {
        "__struct_id": 1,
        "AutoRemoveKey": {
          "type": "byte",
          "value": 0
        },
        "Cursor": {
          "type": "byte",
          "value": 0
        },
        "DisarmDC": {
          "type": "byte",
          "value": 0
        },
        "Faction": {
          "type": "dword",
          "value": 1
        },
        "Geometry": {
          "type": "list",
          "value": [
            {
              "__struct_id": 3,
              "PointX": {
                "type": "float",
                "value": 0.0
              },
              "PointY": {
                "type": "float",
                "value": 0.0
              },
              "PointZ": {
                "type": "float",
                "value": 3.025000095367432
              }
            },
            {
              "__struct_id": 3,
              "PointX": {
                "type": "float",
                "value": 120.7875061035156
              },
              "PointY": {
                "type": "float",
                "value": 4.561953544616699
              },
              "PointZ": {
                "type": "float",
                "value": 3.025000095367432
              }
            },
            {
              "__struct_id": 3,
              "PointX": {
                "type": "float",
                "value": 125.0544204711914
              },
              "PointY": {
                "type": "float",
                "value": 126.5124816894531
              },
              "PointZ": {
                "type": "float",
                "value": 3.025000095367432
              }
            },
            {
              "__struct_id": 3,
              "PointX": {
                "type": "float",
                "value": 1.159071445465088
              },
              "PointY": {
                "type": "float",
                "value": 120.521728515625
              },
              "PointZ": {
                "type": "float",
                "value": 3.025000095367432
              }
            }
          ]
        },
        "HighlightHeight": {
          "type": "float",
          "value": 0.0
        },
        "KeyName": {
          "type": "cexostring",
          "value": ""
        },
        "LinkedTo": {
          "type": "cexostring",
          "value": ""
        },
        "LinkedToFlags": {
          "type": "byte",
          "value": 0
        },
        "LoadScreenID": {
          "type": "word",
          "value": 0
        },
        "LocalizedName": {
          "id": 14759,
          "type": "cexolocstring",
          "value": {
            "0": "No Spawn Zone"
          }
        },
        "OnClick": {
          "type": "resref",
          "value": ""
        },
        "OnDisarm": {
          "type": "resref",
          "value": ""
        },
        "OnTrapTriggered": {
          "type": "resref",
          "value": ""
        },
        "PortraitId": {
          "type": "word",
          "value": 0
        },
        "ScriptHeartbeat": {
          "type": "resref",
          "value": ""
        },
        "ScriptOnEnter": {
          "type": "resref",
          "value": ""
        },
        "ScriptOnExit": {
          "type": "resref",
          "value": ""
        },
        "ScriptUserDefine": {
          "type": "resref",
          "value": ""
        },
        "Tag": {
          "type": "cexostring",
          "value": "anti_spawn_trigg"
        },
        "TemplateResRef": {
          "type": "resref",
          "value": "anti_spawn_trigg"
        },
        "TrapDetectable": {
          "type": "byte",
          "value": 1
        },
        "TrapDetectDC": {
          "type": "byte",
          "value": 0
        },
        "TrapDisarmable": {
          "type": "byte",
          "value": 1
        },
        "TrapFlag": {
          "type": "byte",
          "value": 0
        },
        "TrapOneShot": {
          "type": "byte",
          "value": 1
        },
        "TrapType": {
          "type": "byte",
          "value": 0
        },
        "Type": {
          "type": "int",
          "value": 0
        },
        "XOrientation": {
          "type": "float",
          "value": 0.0
        },
        "XPosition": {
          "type": "float",
          "value": 4.709650993347168
        },
        "YOrientation": {
          "type": "float",
          "value": 0.0
        },
        "YPosition": {
          "type": "float",
          "value": 6.434710502624512
        },
        "ZOrientation": {
          "type": "float",
          "value": 0.0
        },
        "ZPosition": {
          "type": "float",
          "value": 0.0
        }
      }
    ]
  },
  "VarTable": {
    "type": "list",
    "value": [
      {
        "__struct_id": 0,
        "Name": {
          "type": "cexostring",
          "value": "SPACE"
        },
        "Type": {
          "type": "dword",
          "value": 1
        },
        "Value": {
          "type": "int",
          "value": 1
        }
      },
      {
        "__struct_id": 0,
        "Name": {
          "type": "cexostring",
          "value": "RESOURCE_SPAWN_TABLE_ID"
        },
        "Type": {
          "type": "dword",
          "value": 3
        },
        "Value": {
          "type": "cexostring",
          "value": "SPACE_RESOURCES_TATOOINE_ORBIT"
        }
      },
      {
        "__struct_id": 0,
        "Name": {
          "type": "cexostring",
          "value": "CREATURE_SPAWN_TABLE_ID"
        },
        "Type": {
          "type": "dword",
          "value": 3
        },
        "Value": {
          "type": "cexostring",
          "value": "SPACE_TATOOINE_ORBIT"
        }
      },
      {
        "__struct_id": 0,
        "Name": {
          "type": "cexostring",
          "value": "MAP_KEY_ITEM_ID"
        },
        "Type": {
          "type": "dword",
          "value": 1
        },
        "Value": {
          "type": "int",
          "value": 33
        }
      },
      {
        "__struct_id": 0,
        "Name": {
          "type": "cexostring",
          "value": "EXPLORE_ACHIEVEMENT_ID"
        },
        "Type": {
          "type": "dword",
          "value": 1
        },
        "Value": {
          "type": "int",
          "value": 55
        }
      }
    ]
  },
  "WaypointList": {
    "type": "list",
    "value": [
      {
        "__struct_id": 5,
        "Appearance": {
          "type": "byte",
          "value": 1
        },
        "Description": {
          "type": "cexolocstring",
          "value": {}
        },
        "HasMapNote": {
          "type": "byte",
          "value": 0
        },
        "LinkedTo": {
          "type": "cexostring",
          "value": ""
        },
        "LocalizedName": {
          "id": 14817,
          "type": "cexolocstring",
          "value": {
            "0": "Tatooine Orbit"
          }
        },
        "MapNote": {
          "type": "cexolocstring",
          "value": {}
        },
        "MapNoteEnabled": {
          "type": "byte",
          "value": 1
        },
        "Tag": {
          "type": "cexostring",
          "value": "Tatooine_Orbit"
        },
        "TemplateResRef": {
          "type": "resref",
          "value": "nw_waypoint001"
        },
        "XOrientation": {
          "type": "float",
          "value": 0.9852776527404785
        },
        "XPosition": {
          "type": "float",
          "value": 86.40092468261719
        },
        "YOrientation": {
          "type": "float",
          "value": 0.1709619760513306
        },
        "YPosition": {
          "type": "float",
          "value": 54.49938583374023
        },
        "ZPosition": {
          "type": "float",
          "value": 2.999990463256836
        }
      },
      {
        "__struct_id": 5,
        "Appearance": {
          "type": "byte",
          "value": 1
        },
        "Description": {
          "type": "cexolocstring",
          "value": {}
        },
        "HasMapNote": {
          "type": "byte",
          "value": 0
        },
        "LinkedTo": {
          "type": "cexostring",
          "value": ""
        },
        "LocalizedName": {
          "id": 14817,
          "type": "cexolocstring",
          "value": {}
        },
        "MapNote": {
          "type": "cexolocstring",
          "value": {}
        },
        "MapNoteEnabled": {
          "type": "byte",
          "value": 1
        },
        "Tag": {
          "type": "cexostring",
          "value": "STARLANE_LANDING_TATOOINE_1"
        },
        "TemplateResRef": {
          "type": "resref",
          "value": "nw_waypoint001"
        },
        "XOrientation": {
          "type": "float",
          "value": -0.6343931555747986
        },
        "XPosition": {
          "type": "float",
          "value": 295.7915954589844
        },
        "YOrientation": {
          "type": "float",
          "value": 0.7730105519294739
        },
        "YPosition": {
          "type": "float",
          "value": 23.63143730163574
        },
        "ZPosition": {
          "type": "float",
          "value": 2.999990463256836
        }
      }
    ]
  }
}
