{
  "__data_type": "UTI ",
  "AddCost": {
    "type": "dword",
    "value": 0
  },
  "BaseItem": {
    "type": "int",
    "value": 22
  },
  "Charges": {
    "type": "byte",
    "value": 0
  },
  "Comment": {
    "type": "cexostring",
    "value": "1"
  },
  "Cost": {
    "type": "dword",
    "value": 200002
  },
  "Cursed": {
    "type": "byte",
    "value": 1
  },
  "DescIdentified": {
    "type": "cexolocstring",
    "value": {}
  },
  "Description": {
    "type": "cexolocstring",
    "value": {
      "0": ""
    }
  },
  "Identified": {
    "type": "byte",
    "value": 1
  },
  "LocalizedName": {
    "id": 191,
    "type": "cexolocstring",
    "value": {
      "0": "Ro Solus's Knife"
    }
  },
  "ModelPart1": {
    "type": "byte",
    "value": 24
  },
  "ModelPart2": {
    "type": "byte",
    "value": 64
  },
  "ModelPart3": {
    "type": "byte",
    "value": 14
  },
  "PaletteID": {
    "type": "byte",
    "value": 34
  },
  "Plot": {
    "type": "byte",
    "value": 1
  },
  "PropertiesList": {
    "type": "list",
    "value": [
      {
        "__struct_id": 0,
        "ChanceAppear": {
          "type": "byte",
          "value": 100
        },
        "CostTable": {
          "type": "byte",
          "value": 1
        },
        "CostValue": {
          "type": "word",
          "value": 10
        },
        "Param1": {
          "type": "byte",
          "value": 255
        },
        "Param1Value": {
          "type": "byte",
          "value": 0
        },
        "PropertyName": {
          "type": "word",
          "value": 0
        },
        "Subtype": {
          "type": "word",
          "value": 0
        }
      },
      {
        "__struct_id": 0,
        "ChanceAppear": {
          "type": "byte",
          "value": 100
        },
        "CostTable": {
          "type": "byte",
          "value": 2
        },
        "CostValue": {
          "type": "word",
          "value": 20
        },
        "Param1": {
          "type": "byte",
          "value": 255
        },
        "Param1Value": {
          "type": "byte",
          "value": 0
        },
        "PropertyName": {
          "type": "word",
          "value": 56
        },
        "Subtype": {
          "type": "word",
          "value": 0
        }
      },
      {
        "__struct_id": 0,
        "ChanceAppear": {
          "type": "byte",
          "value": 100
        },
        "CostTable": {
          "type": "byte",
          "value": 4
        },
        "CostValue": {
          "type": "word",
          "value": 20
        },
        "Param1": {
          "type": "byte",
          "value": 255
        },
        "Param1Value": {
          "type": "byte",
          "value": 0
        },
        "PropertyName": {
          "type": "word",
          "value": 16
        },
        "Subtype": {
          "type": "word",
          "value": 1
        }
      },
      {
        "__struct_id": 0,
        "ChanceAppear": {
          "type": "byte",
          "value": 100
        },
        "CostTable": {
          "type": "byte",
          "value": 4
        },
        "CostValue": {
          "type": "word",
          "value": 20
        },
        "Param1": {
          "type": "byte",
          "value": 255
        },
        "Param1Value": {
          "type": "byte",
          "value": 0
        },
        "PropertyName": {
          "type": "word",
          "value": 16
        },
        "Subtype": {
          "type": "word",
          "value": 2
        }
      },
      {
        "__struct_id": 0,
        "ChanceAppear": {
          "type": "byte",
          "value": 100
        },
        "CostTable": {
          "type": "byte",
          "value": 2
        },
        "CostValue": {
          "type": "word",
          "value": 10
        },
        "Param1": {
          "type": "byte",
          "value": 255
        },
        "Param1Value": {
          "type": "byte",
          "value": 0
        },
        "PropertyName": {
          "type": "word",
          "value": 6
        },
        "Subtype": {
          "type": "word",
          "value": 0
        }
      },
      {
        "__struct_id": 0,
        "ChanceAppear": {
          "type": "byte",
          "value": 100
        },
        "CostTable": {
          "type": "byte",
          "value": 0
        },
        "CostValue": {
          "type": "word",
          "value": 0
        },
        "Param1": {
          "type": "byte",
          "value": 255
        },
        "Param1Value": {
          "type": "byte",
          "value": 0
        },
        "PropertyName": {
          "type": "word",
          "value": 43
        },
        "Subtype": {
          "type": "word",
          "value": 0
        }
      },
      {
        "__struct_id": 0,
        "ChanceAppear": {
          "type": "byte",
          "value": 100
        },
        "CostTable": {
          "type": "byte",
          "value": 4
        },
        "CostValue": {
          "type": "word",
          "value": 12
        },
        "Param1": {
          "type": "byte",
          "value": 255
        },
        "Param1Value": {
          "type": "byte",
          "value": 0
        },
        "PropertyName": {
          "type": "word",
          "value": 74
        },
        "Subtype": {
          "type": "word",
          "value": 0
        }
      },
      {
        "__struct_id": 0,
        "ChanceAppear": {
          "type": "byte",
          "value": 100
        },
        "CostTable": {
          "type": "byte",
          "value": 0
        },
        "CostValue": {
          "type": "word",
          "value": 0
        },
        "Param1": {
          "type": "byte",
          "value": 255
        },
        "Param1Value": {
          "type": "byte",
          "value": 0
        },
        "PropertyName": {
          "type": "word",
          "value": 127
        },
        "Subtype": {
          "type": "word",
          "value": 0
        }
      },
      {
        "__struct_id": 0,
        "ChanceAppear": {
          "type": "byte",
          "value": 100
        },
        "CostTable": {
          "type": "byte",
          "value": 0
        },
        "CostValue": {
          "type": "word",
          "value": 0
        },
        "Param1": {
          "type": "byte",
          "value": 255
        },
        "Param1Value": {
          "type": "byte",
          "value": 0
        },
        "PropertyName": {
          "type": "word",
          "value": 127
        },
        "Subtype": {
          "type": "word",
          "value": 0
        }
      },
      {
        "__struct_id": 0,
        "ChanceAppear": {
          "type": "byte",
          "value": 100
        },
        "CostTable": {
          "type": "byte",
          "value": 24
        },
        "CostValue": {
          "type": "word",
          "value": 6
        },
        "Param1": {
          "type": "byte",
          "value": 10
        },
        "Param1Value": {
          "type": "byte",
          "value": 2
        },
        "PropertyName": {
          "type": "word",
          "value": 48
        },
        "Subtype": {
          "type": "word",
          "value": 19
        }
      }
    ]
  },
  "StackSize": {
    "type": "word",
    "value": 1
  },
  "Stolen": {
    "type": "byte",
    "value": 0
  },
  "Tag": {
    "type": "cexostring",
    "value": "solusdagger"
  },
  "TemplateResRef": {
    "type": "resref",
    "value": "solusknife"
  }
}
