{
  "__data_type": "UTI ",
  "AddCost": {
    "type": "dword",
    "value": 0
  },
  "BaseItem": {
    "type": "int",
    "value": 73
  },
  "Charges": {
    "type": "byte",
    "value": 0
  },
  "Comment": {
    "type": "cexostring",
    "value": ""
  },
  "Cost": {
    "type": "dword",
    "value": 0
  },
  "Cursed": {
    "type": "byte",
    "value": 0
  },
  "DescIdentified": {
    "type": "cexolocstring",
    "value": {}
  },
  "Description": {
    "type": "cexolocstring",
    "value": {}
  },
  "Identified": {
    "type": "byte",
    "value": 0
  },
  "LocalizedName": {
    "type": "cexolocstring",
    "value": {
      "0": "Sith Warrior T2 Skin"
    }
  },
  "ModelPart1": {
    "type": "byte",
    "value": 1
  },
  "PaletteID": {
    "type": "byte",
    "value": 14
  },
  "Plot": {
    "type": "byte",
    "value": 0
  },
  "PropertiesList": {
    "type": "list",
    "value": [
      {
        "__struct_id": 0,
        "ChanceAppear": {
          "type": "byte",
          "value": 100
        },
        "CostTable": {
          "type": "byte",
          "value": 35
        },
        "CostValue": {
          "type": "word",
          "value": 45
        },
        "Param1": {
          "type": "byte",
          "value": 255
        },
        "Param1Value": {
          "type": "byte",
          "value": 0
        },
        "PropertyName": {
          "type": "word",
          "value": 94
        },
        "Subtype": {
          "type": "word",
          "value": 2
        }
      },
      {
        "__struct_id": 0,
        "ChanceAppear": {
          "type": "byte",
          "value": 100
        },
        "CostTable": {
          "type": "byte",
          "value": 35
        },
        "CostValue": {
          "type": "word",
          "value": 45
        },
        "Param1": {
          "type": "byte",
          "value": 255
        },
        "Param1Value": {
          "type": "byte",
          "value": 0
        },
        "PropertyName": {
          "type": "word",
          "value": 94
        },
        "Subtype": {
          "type": "word",
          "value": 1
        }
      },
      {
        "__struct_id": 0,
        "ChanceAppear": {
          "type": "byte",
          "value": 100
        },
        "CostTable": {
          "type": "byte",
          "value": 40
        },
        "CostValue": {
          "type": "word",
          "value": 100
        },
        "Param1": {
          "type": "byte",
          "value": 255
        },
        "Param1Value": {
          "type": "byte",
          "value": 0
        },
        "PropertyName": {
          "type": "word",
          "value": 97
        },
        "Subtype": {
          "type": "word",
          "value": 0
        }
      },
      {
        "__struct_id": 0,
        "ChanceAppear": {
          "type": "byte",
          "value": 100
        },
        "CostTable": {
          "type": "byte",
          "value": 43
        },
        "CostValue": {
          "type": "word",
          "value": 45
        },
        "Param1": {
          "type": "byte",
          "value": 255
        },
        "Param1Value": {
          "type": "byte",
          "value": 0
        },
        "PropertyName": {
          "type": "word",
          "value": 99
        },
        "Subtype": {
          "type": "word",
          "value": 0
        }
      },
      {
        "__struct_id": 0,
        "ChanceAppear": {
          "type": "byte",
          "value": 100
        },
        "CostTable": {
          "type": "byte",
          "value": 41
        },
        "CostValue": {
          "type": "word",
          "value": 100
        },
        "Param1": {
          "type": "byte",
          "value": 255
        },
        "Param1Value": {
          "type": "byte",
          "value": 0
        },
        "PropertyName": {
          "type": "word",
          "value": 98
        },
        "Subtype": {
          "type": "word",
          "value": 0
        }
      }
    ]
  },
  "StackSize": {
    "type": "word",
    "value": 1
  },
  "Stolen": {
    "type": "byte",
    "value": 0
  },
  "Tag": {
    "type": "cexostring",
    "value": "SithWarriorT2Skin"
  },
  "TemplateResRef": {
    "type": "resref",
    "value": "vnpcswar2"
  }
}
